vtb_django_utils/__init__.py
vtb_django_utils/backends.py
vtb_django_utils/keycloak_utils.py
vtb_django_utils/views.py
vtb_django_utils/drf/__init__.py
vtb_django_utils/drf/auth.py
vtb_django_utils/drf/max_limit_offset_pagination.py
vtb_django_utils/drf/views.py
vtb_django_utils/model_dump/__init__.py
vtb_django_utils/model_dump/admin.py
vtb_django_utils/model_dump/apps.py
vtb_django_utils/model_dump/consts.py
vtb_django_utils/model_dump/dump.py
vtb_django_utils/model_dump/exceptions.py
vtb_django_utils/model_dump/load.py
vtb_django_utils/model_dump/utils.py
vtb_django_utils/model_dump/views.py
vtb_django_utils/model_dump/convert_versions/__init__.py
vtb_django_utils/model_dump/convert_versions/convert_v5_to_v4.py
vtb_django_utils/model_dump/templates/__init__.py
vtb_django_utils/model_dump/templates/change_list.html
vtb_django_utils/model_dump/templates/confirm_pinned_version.html
vtb_django_utils/model_dump/templates/export_instance.html
vtb_django_utils/model_dump/templates/load_instance.html
vtb_django_utils/model_versions/__init__.py
vtb_django_utils/model_versions/admin.py
vtb_django_utils/model_versions/apps.py
vtb_django_utils/model_versions/models.py
vtb_django_utils/model_versions/serializers.py
vtb_django_utils/model_versions/views.py
vtb_django_utils/model_versions/templates/__init__.py
vtb_django_utils/model_versions/templates/get_version_name.html
vtb_django_utils/model_versions/utils/__init__.py
vtb_django_utils/model_versions/utils/consts.py
vtb_django_utils/model_versions/utils/enums.py
vtb_django_utils/model_versions/utils/inspect.py
vtb_django_utils/model_versions/utils/models.py
vtb_django_utils/model_versions/utils/regex.py
vtb_django_utils/model_versions/utils/serializer_validators.py
vtb_django_utils/model_versions/utils/serializers.py
vtb_django_utils/model_versions/utils/strings.py
vtb_django_utils/user_info/__init__.py
vtb_django_utils/user_info/consts.py
vtb_django_utils/user_info/info.py
vtb_django_utils/user_info/middleware.py
vtb_django_utils-2.0.33.dist-info/METADATA
vtb_django_utils-2.0.33.dist-info/WHEEL
vtb_django_utils-2.0.33.dist-info/top_level.txt
vtb_django_utils-2.0.33.dist-info/RECORD
