Metadata-Version: 2.1
Name: vtb-django-utils
Version: 2.0.33
Summary: django utils for VTB projects
Home-page: https://bitbucket.region.vtb.ru/projects/PUOS/repos/vtb-django-utils
Author: VTB
Author-email: 
License: UNKNOWN
Platform: UNKNOWN
Classifier: Programming Language :: Python :: 3.8
Classifier: Framework :: Django :: 3.0
Classifier: Operating System :: OS Independent
Requires-Dist: vtb-http-interaction (>=0.1.3)
Requires-Dist: django (>=3.0.0)
Requires-Dist: djangorestframework (>=3.12.2)
Requires-Dist: mozilla-django-oidc (==1.2.4)
Requires-Dist: django-lifecycle (==0.8.0)
Requires-Dist: pytz (==2021.3)
Provides-Extra: test
Requires-Dist: pytest ; extra == 'test'
Requires-Dist: pytest-env ; extra == 'test'
Requires-Dist: pylint ; extra == 'test'
Requires-Dist: pytest-asyncio ; extra == 'test'
